{
	"configurations" : 
	[
		{
			"directories" : 
			[
				{
					"build" : ".",
					"childIndexes" : 
					[
						1
					],
					"minimumCMakeVersion" : 
					{
						"string" : "3.14"
					},
					"projectIndex" : 0,
					"source" : "."
				},
				{
					"build" : "dummy",
					"childIndexes" : 
					[
						2,
						3
					],
					"minimumCMakeVersion" : 
					{
						"string" : "3.12"
					},
					"parentIndex" : 0,
					"projectIndex" : 1,
					"source" : "dummy"
				},
				{
					"build" : "dummy/src",
					"minimumCMakeVersion" : 
					{
						"string" : "3.12"
					},
					"parentIndex" : 1,
					"projectIndex" : 1,
					"source" : "dummy/src",
					"targetIndexes" : 
					[
						1
					]
				},
				{
					"build" : "dummy/app",
					"minimumCMakeVersion" : 
					{
						"string" : "3.12"
					},
					"parentIndex" : 1,
					"projectIndex" : 1,
					"source" : "dummy/app",
					"targetIndexes" : 
					[
						0
					]
				}
			],
			"name" : "Debug",
			"projects" : 
			[
				{
					"childIndexes" : 
					[
						1
					],
					"directoryIndexes" : 
					[
						0
					],
					"name" : "AdvancedCProgrammingCourse"
				},
				{
					"directoryIndexes" : 
					[
						1,
						2,
						3
					],
					"name" : "dummy_Project",
					"parentIndex" : 0,
					"targetIndexes" : 
					[
						0,
						1
					]
				}
			],
			"targets" : 
			[
				{
					"directoryIndex" : 3,
					"id" : "dummy_Executable::@4c9f7f4eb2508940f8be",
					"jsonFile" : "target-dummy_Executable-Debug-fd703dffc71cbed819e8.json",
					"name" : "dummy_Executable",
					"projectIndex" : 1
				},
				{
					"directoryIndex" : 2,
					"id" : "dummy_MyLib::@fe9a1ccf74a65cf841a2",
					"jsonFile" : "target-dummy_MyLib-Debug-cf21125a52c8c77b115f.json",
					"name" : "dummy_MyLib",
					"projectIndex" : 1
				}
			]
		}
	],
	"kind" : "codemodel",
	"paths" : 
	{
		"build" : "C:/Users/eywiotosof/Documents/GitHub/SmallConstructionsInCpp/build",
		"source" : "C:/Users/eywiotosof/Documents/GitHub/SmallConstructionsInCpp"
	},
	"version" : 
	{
		"major" : 2,
		"minor" : 2
	}
}
